{
  "gitSyncId": "69a59102e5a8525f403966eb_714d4e89-ac2a-4f57-b3d8-8f9c575ef10d",
  "id": "Analytics_EnergyConsumptionHelper.getLocationChartConfig",
  "pluginId": "js-plugin",
  "pluginType": "JS",
  "unpublishedAction": {
    "actionConfiguration": {
      "encodeParamsToggle": true,
      "jsArguments": [],
      "paginationType": "NONE",
      "timeoutInMillisecond": 10000
    },
    "collectionId": "Analytics_EnergyConsumptionHelper",
    "confirmBeforeExecute": false,
    "datasource": {
      "isAutoGenerated": false,
      "name": "UNUSED_DATASOURCE",
      "pluginId": "js-plugin"
    },
    "dynamicBindingPathList": [
      {
        "key": "body"
      }
    ],
    "fullyQualifiedName": "EnergyConsumptionHelper.getLocationChartConfig",
    "name": "getLocationChartConfig",
    "pageId": "Analytics",
    "runBehaviour": "MANUAL",
    "userSetOnLoad": false
  }
}