{
  "backgroundColor": "#FFFFFF",
  "borderColor": "#E0DEDE",
  "borderRadius": "{{appsmith.theme.borderRadius.appBorderRadius}}",
  "borderWidth": "1",
  "bottomRow": 215,
  "boxShadow": "{{appsmith.theme.boxShadow.appBoxShadow}}",
  "defaultModel": "{{\n{\n  data: getBill.data\n}\n}}",
  "dynamicBindingPathList": [
    {
      "key": "theme"
    },
    {
      "key": "borderRadius"
    },
    {
      "key": "boxShadow"
    },
    {
      "key": "defaultModel"
    }
  ],
  "dynamicHeight": "AUTO_HEIGHT",
  "dynamicPropertyPathList": [
    {
      "key": "onResetClick"
    }
  ],
  "dynamicTriggerPathList": [
    {
      "key": "onResetClick"
    }
  ],
  "events": [
    "onResetClick"
  ],
  "isCanvas": false,
  "isLoading": false,
  "isSearchWildcard": true,
  "isVisible": true,
  "key": "tsvhyrr8qx",
  "leftColumn": 0,
  "maxDynamicHeight": 9000,
  "minDynamicHeight": 4,
  "mobileBottomRow": 38,
  "mobileLeftColumn": 0,
  "mobileRightColumn": 8,
  "mobileTopRow": 8,
  "needsErrorInfo": false,
  "onResetClick": "{{showAlert('Successfully reset!!', '');}}",
  "originalBottomRow": 226,
  "originalTopRow": 2,
  "parentColumnSpace": 10.421357154846191,
  "parentId": "7tntsa5sim",
  "parentRowSpace": 10,
  "renderMode": "CANVAS",
  "rightColumn": 64,
  "shouldScrollContents": true,
  "srcDoc": {
    "css": "@charset \"UTF-8\";\nbody {\n  margin: 0;\n  font-family: \"Inter\", \"Segoe UI\", Arial, sans-serif;\n}\n\n/* ===== Header Bar ===== */\n.header-bar {\n  display: flex;\n  align-items: center;\n  background-color: #001f54;\n  color: #fff;\n  font-size: 13px;\n  font-weight: 500;\n  padding: 6px 10px;\n  flex-wrap: wrap;\n  border-radius: 4px 4px 0 0;\n}\n\n.header-item {\n  padding: 4px 10px;\n  border-right: 1px solid rgba(255, 255, 255, 0.2);\n}\n\n.header-item:last-child {\n  border-right: none;\n}\n\n.header-item.title {\n  font-weight: 600;\n  display: inline-flex;\n  align-items: center;\n  gap: 4px;\n  text-transform: capitalize;\n  background: #082E69;\n  justify-content: center;\n}\n\n.utility-title svg {\n  stroke: #fff;\n  vertical-align: middle;\n  position: relative;\n  top: -1px;\n}\n\n/* ===== General Info + Calculation Container Shared Style ===== */\n.general-info,\n.calc-container {\n  background: #fff;\n  border-radius: 6px;\n  padding: 16px 20px;\n  margin: 12px;\n  box-shadow: 0 2px 6px rgba(0, 0, 0, 0.08);\n  color: #0a0a0a;\n}\n\n.general-info h3,\n.calc-container h3 {\n  font-weight: 700;\n  font-size: 16px;\n  color: #002050;\n  margin-bottom: 12px;\n}\n\n/* ===== Info Grid (2 columns) ===== */\n.info-grid {\n  display: grid;\n  grid-template-columns: 1fr 1fr;\n  gap: 10px 20px;\n}\n\n.info-column {\n  display: flex;\n  flex-direction: column;\n  gap: 4px;\n}\n\n/* ===== Info Row ===== */\n.info-row {\n  display: flex;\n  justify-content: space-between;\n  align-items: center;\n  padding: 6px 10px;\n  font-size: 13px;\n  border-bottom: 1px solid #f1f2f4;\n  border-radius: 2px;\n  background-color: #fff;\n}\n\n.info-row:nth-child(odd) {\n  background-color: #F1F2F4;\n}\n\n.info-label {\n  font-weight: 600;\n  color: #222;\n  flex: 1;\n  white-space: nowrap;\n}\n\n.info-value {\n  flex: 1;\n  text-align: right;\n  color: #111;\n  font-weight: 500;\n}\n\n.unit {\n  color: #666;\n  font-size: 12px;\n  margin-left: 3px;\n}\n\n/* ===== No Data ===== */\n.no-data {\n  text-align: center;\n  color: #777;\n  font-style: italic;\n  padding: 12px;\n}\n\n/* ===== Usage Section ===== */\n.usage-section {\n  margin-top: 20px;\n}\n\n.usage-section h3 {\n  font-weight: 700;\n  font-size: 15px;\n  color: #002050;\n  margin-bottom: 10px;\n}\n\n.usage-table {\n  width: 100%;\n  border-collapse: collapse;\n  font-size: 13px;\n}\n\n.usage-table th {\n  text-align: left;\n  background-color: #f1f4f8;\n  color: #002050;\n  font-weight: 600;\n  padding: 8px 10px;\n}\n\n.usage-table td {\n  padding: 8px 10px;\n  border-top: 1px solid #eee;\n}\n\n.usage-table tr:nth-child(odd) {\n  background-color: #F1F2F4;\n}\n\n/* ===== Calculation Section ===== */\n.calc-section {\n  margin-top: 20px;\n}\n\n.calc-section h4 {\n  font-size: 14px;\n  font-weight: 600;\n  color: #0a0a0a;\n  margin-bottom: 16px;\n}\n\n/* ===== Collapsible Section Headers ===== */\n.collapsible-header,\n.calc-header {\n  cursor: pointer;\n  user-select: none;\n}\n\n.arrow {\n  display: inline-block;\n  font-size: 18px;\n  transition: transform 0.3s ease;\n  transform: rotate(-90deg); /* Default → right */\n  margin-right: 6px;\n}\n\n.arrow.open {\n  transform: rotate(0deg); /* Open ↓ down */\n}\n\n/* ===== Slide Animation ===== */\n.slide-section {\n  max-height: 0;\n  opacity: 0;\n  overflow: hidden;\n  transform: translateY(-5px);\n  transition: all 0.4s ease-in-out;\n}\n\n.slide-section.open {\n  max-height: fit-content;\n  opacity: 1;\n  transform: translateY(0);\n  padding-bottom: 10px;\n}\n\n.sub-container {\n  background-color: #F8FAFC;\n}\n\n/* ===== Filter Bar with Selects ===== */\n.filter-bar {\n  background: #f8fafc;\n  border: 1px solid #d9e2ec;\n  border-radius: 6px;\n  padding: 10px 16px;\n  margin: 10px 12px 20px;\n  box-shadow: 0 1px 4px rgba(0, 0, 0, 0.05);\n}\n\n.filter-row {\n  display: flex;\n  gap: 10px;\n  flex-wrap: wrap;\n  align-items: center;\n}\n\n.filter-row select {\n  flex: 1;\n  min-width: 160px;\n  padding: 10px;\n  border: 1px solid #cbd5e1;\n  border-radius: 4px;\n  font-size: 13px;\n  background: #fff;\n  color: #0a0a0a;\n  cursor: pointer;\n}\n\n.filter-row select:focus {\n  border-color: #2563eb;\n  box-shadow: 0 0 0 2px rgba(37, 99, 235, 0.15);\n}\n\n.filter-row button {\n  background-color: #001f54;\n  color: #fff;\n  border: none;\n  border-radius: 4px;\n  padding: 6px 12px;\n  cursor: pointer;\n  font-size: 13px;\n  font-weight: 600;\n}\n\n.filter-row button:hover {\n  background-color: #003c8f;\n}\n\n/* === Top Toolbar === */\n.top-toolbar {\n  display: flex;\n  justify-content: space-between;\n  align-items: center;\n  padding: 8px 0px 0px 10px;\n}\n\n.bill-count {\n  font-size: 14px;\n  color: #001f54;\n}\n\n.toolbar-right {\n  display: flex;\n  align-items: center;\n  gap: 8px;\n}\n\n.icon-btn {\n  background: transparent;\n  border: none;\n  padding: 6px 10px;\n  display: flex;\n  align-items: center;\n  gap: 6px;\n  cursor: pointer;\n  color: #001f54;\n  font-weight: 600;\n  transition: background 0.2s ease;\n}\n\n.filters {\n  background: #F1F2F4;\n  border: 1px solid #F1F2F4;\n  border-radius: 3px;\n}\n\n.filters svg {\n  height: 24px;\n}\n\n.filters:hover {\n  color: #1846b0;\n}\n\n.filter-label {\n  font-size: 13px;\n}\n\n/* === Filter Bar Hide/Show Animation === */\n.filter-bar-wrapper {\n  max-height: 0;\n  overflow: hidden;\n  transition: max-height 0.4s ease;\n}\n\n.filter-bar-wrapper.open {\n  max-height: 200px;\n  transition: max-height 0.4s ease;\n}\n\n/* ========== Filter Bar Container ========== */\n.filter-bar-container {\n  background: #F1F2F4;\n  border-radius: 6px;\n  box-shadow: 0 2px 6px rgba(0, 0, 0, 0.08);\n  margin: 0px 0 20px;\n  padding: 0 16px;\n  overflow: hidden;\n  max-height: 0;\n  opacity: 0;\n  transform: translateY(-8px);\n  transition: all 0.4s ease-in-out;\n}\n\n.filter-bar-container.open {\n  max-height: 500px;\n  opacity: 1;\n  transform: translateY(0);\n  padding-top: 16px;\n  padding-bottom: 16px;\n}\n\n/* ========== Grid Layout for Select Boxes ========== */\n.filter-grid {\n  display: grid;\n  grid-template-columns: repeat(3, 1fr);\n  gap: 12px 20px;\n}\n\n.filter-item select {\n  width: 100%;\n  padding: 6px 8px;\n  font-size: 13px;\n  border-radius: 4px;\n  border: 1px solid #ccc;\n  background: #fff;\n  color: #222;\n}\n\n/* ========== Responsive Grid ========== */\n@media (max-width: 600px) {\n  .filter-grid {\n    grid-template-columns: repeat(2, 1fr);\n  }\n}\n@media (max-width: 300px) {\n  .filter-grid {\n    grid-template-columns: 1fr;\n  }\n}\n/* ========== Footer ========== */\n.filter-footer {\n  display: flex;\n  justify-content: flex-end;\n  margin-top: 16px;\n}\n\n.clear-btn {\n  background: transparent;\n  color: #1846b0;\n  border: none;\n  padding: 6px 12px;\n  font-weight: 600;\n  font-size: 13px;\n  cursor: pointer;\n  transition: background 0.3s;\n  text-decoration: underline;\n}\n\n/* ===== Responsive ===== */\n/* @media (max-width: 768px) {\n  .info-grid {\n    grid-template-columns: 1fr;\n  }\n}*/",
    "html": "<!-- no need to write html, head, body tags, it is handled by the widget -->\n<div id=\"root\"></div>\n",
    "js": "function _extends() { return _extends = Object.assign ? Object.assign.bind() : function (n) { for (var e = 1; e < arguments.length; e++) { var t = arguments[e]; for (var r in t) ({}).hasOwnProperty.call(t, r) && (n[r] = t[r]); } return n; }, _extends.apply(null, arguments); }\nimport React, { useState, useEffect, useMemo } from \"https://esm.sh/react@18.2.0\";\nimport ReactDOM from \"https://esm.sh/react-dom@18.2.0\";\nimport * as LucideIcons from \"https://esm.sh/lucide-react@0.292.0\";\n\n// ------------------------- Info Row -------------------------\nfunction InfoRow({\n  label,\n  value\n}) {\n  return /*#__PURE__*/React.createElement(\"div\", {\n    className: \"info-row\"\n  }, /*#__PURE__*/React.createElement(\"span\", {\n    className: \"info-label\"\n  }, label), /*#__PURE__*/React.createElement(\"span\", {\n    className: \"info-value\"\n  }, value));\n}\n\n// ------------------------- Usage Table -------------------------\nfunction UsageTable({\n  usageData\n}) {\n  if (!usageData?.length) return null;\n  return /*#__PURE__*/React.createElement(\"div\", {\n    className: \"usage-section\"\n  }, /*#__PURE__*/React.createElement(\"h3\", null, \"Usage Charges\"), /*#__PURE__*/React.createElement(\"table\", {\n    className: \"usage-table\"\n  }, /*#__PURE__*/React.createElement(\"tbody\", null, usageData.map((row, i) => /*#__PURE__*/React.createElement(\"tr\", {\n    key: i\n  }, /*#__PURE__*/React.createElement(\"td\", null, row.value || \"-\"), /*#__PURE__*/React.createElement(\"td\", null, row.usage || \"-\"), /*#__PURE__*/React.createElement(\"td\", null, row.uom || \"-\"), /*#__PURE__*/React.createElement(\"td\", null, /*#__PURE__*/React.createElement(\"b\", null, \"$\", row.charge?.toFixed(2) || \"0.00\")), /*#__PURE__*/React.createElement(\"td\", null, row.description || \"-\"))))));\n}\n\n// ------------------------- Calculation Box -------------------------\nfunction CalculationBox({\n  title,\n  values\n}) {\n  if (!values?.length) return null;\n  const midIndex = Math.ceil(values.length / 2);\n  const leftValues = values.slice(0, midIndex);\n  const rightValues = values.slice(midIndex);\n  return /*#__PURE__*/React.createElement(\"div\", {\n    className: \"calc-section\"\n  }, /*#__PURE__*/React.createElement(\"h4\", null, title), /*#__PURE__*/React.createElement(\"div\", {\n    className: \"info-grid\"\n  }, /*#__PURE__*/React.createElement(\"div\", {\n    className: \"info-column\"\n  }, leftValues.map((item, i) => /*#__PURE__*/React.createElement(InfoRow, {\n    key: i,\n    label: item.name || \"-\",\n    value: /*#__PURE__*/React.createElement(React.Fragment, null, item.value || \"-\", \" \", /*#__PURE__*/React.createElement(\"span\", {\n      className: \"unit\"\n    }, item.units || \"\"))\n  }))), /*#__PURE__*/React.createElement(\"div\", {\n    className: \"info-column\"\n  }, rightValues.map((item, i) => /*#__PURE__*/React.createElement(InfoRow, {\n    key: i,\n    label: item.name || \"-\",\n    value: /*#__PURE__*/React.createElement(React.Fragment, null, item.value || \"-\", \" \", /*#__PURE__*/React.createElement(\"span\", {\n      className: \"unit\"\n    }, item.units || \"\"))\n  })))));\n}\n\n// ------------------------- Bill Record -------------------------\nfunction BillRecord({\n  record,\n  collapseAll\n}) {\n  const [showHeader, setShowHeader] = useState(true);\n  const [showCalc, setShowCalc] = useState(false);\n  useEffect(() => {\n    setShowHeader(!collapseAll);\n  }, [collapseAll]);\n  const usage = record.usage || [];\n  const weatherValues = record.weathervalues || [];\n  const dailyAverageValues = (record.regulardailyvalues || []).filter(v => v.name?.toLowerCase().includes(\"daily\"));\n  const regularValues = (record.regulardailyvalues || []).filter(v => !v.name?.toLowerCase().includes(\"daily\"));\n  const headerData = {\n    title: record.utility_type?.charAt(0).toUpperCase() + record.utility_type?.slice(1).toLowerCase(),\n    mid: record.meter_id || \"-\",\n    said: record.service_account_id || \"-\",\n    ratePlan: record.rate_plan || \"-\",\n    locationDescription: record.location_description || \"-\",\n    dateRange: record.billing_start_date && record.billing_end_date ? `${record.billing_start_date} - ${record.billing_end_date}` : \"-\",\n    subtotal: `$${record.current_charges || \"0.00\"}`\n  };\n  const infoLeft = [{\n    label: \"Bill SubTotal\",\n    value: `$${record.current_charges || \"-\"}`\n  }, {\n    label: \"Virtual Account Id\",\n    value: record.virtual_account_id || \"-\"\n  }, {\n    label: \"Service Account Id\",\n    value: record.service_account_id || \"-\"\n  }, {\n    label: \"Service Address\",\n    value: record.service_address || \"-\"\n  }, {\n    label: \"Service Zip\",\n    value: record.service_zip || \"-\"\n  }, {\n    label: \"Meter Id\",\n    value: record.meter_id || \"-\"\n  }, {\n    label: \"Delivery Location\",\n    value: record.delivery_location || \"-\"\n  }, {\n    label: \"Vendor Type\",\n    value: record.vendor_type || \"-\"\n  }, {\n    label: \"Location Address\",\n    value: record.location_address || \"-\"\n  }];\n  const infoRight = [{\n    label: \"Location Description\",\n    value: record.location_description || \"-\"\n  }, {\n    label: \"Division\",\n    value: record.division || \"-\"\n  }, {\n    label: \"Service Start Date\",\n    value: record.billing_start_date || \"-\"\n  }, {\n    label: \"Service End Date\",\n    value: record.billing_end_date || \"-\"\n  }, {\n    label: \"Days Of Service\",\n    value: record.days_of_service && record.service_date_method ? `${record.days_of_service} (${record.service_date_method})` : \"-\"\n  }, {\n    label: \"Adjusted Service End Date\",\n    value: record.adjusted_service_end_date || \"-\"\n  }, {\n    label: \"Rate Plan\",\n    value: record.rate_plan || \"-\"\n  }, {\n    label: \"Estimated\",\n    value: record.estimated ? \"YES\" : \"NO\"\n  }, {\n    label: \"Prior Meter Reading\",\n    value: record.prior_meter_reading || \"-\"\n  }];\n  const utilityIcons = {\n    CABLE: \"Tv\",\n    CARBONDIOXIDE: \"Wind\",\n    CHILLEDWATER: \"Snowflake\",\n    DIESEL: \"Fuel\",\n    ELECTRIC: \"Zap\",\n    FIREPROTECTION: \"Shield\",\n    FUELCELL: \"Battery\",\n    HOTWATER: \"Flame\",\n    INTERNET: \"Wifi\",\n    IRRIGATION: \"Sprout\",\n    LIGHTING: \"Lightbulb\",\n    NATURALGAS: \"Flame\",\n    NG_COGEN: \"Factory\",\n    NITROGEN: \"FlaskConical\",\n    OIL2: \"Fuel\",\n    OIL4: \"Fuel\",\n    OIL6: \"Fuel\",\n    OTHER: \"Package\",\n    OXYGEN: \"Activity\",\n    PESTCONTROL: \"Bug\",\n    PROPANE: \"Flame\",\n    REFUSE: \"Trash2\",\n    SEWER: \"Waves\",\n    SOLARPV: \"Haze\",\n    STEAM: \"CloudFog\",\n    STORMDRAIN: \"CloudRain\",\n    STORMWATER: \"CloudRainWind\",\n    TELEPHONE: \"UtilityPole\",\n    UNLEADEDFUEL: \"Fuel\",\n    UTILITYGAS: \"Flame\",\n    WATER: \"Droplet\"\n  };\n  const iconName = utilityIcons[record.utility_type?.toUpperCase()] || \"Factory\";\n  const Icon = LucideIcons[iconName];\n  return /*#__PURE__*/React.createElement(\"div\", {\n    className: \"container\"\n  }, /*#__PURE__*/React.createElement(\"div\", {\n    className: \"header-bar collapsible-header\",\n    onClick: () => setShowHeader(!showHeader)\n  }, /*#__PURE__*/React.createElement(\"span\", {\n    className: `arrow ${showHeader ? \"open\" : \"\"}`\n  }, \"\\u25BE\"), /*#__PURE__*/React.createElement(\"div\", {\n    className: \"header-item title utility-title\"\n  }, /*#__PURE__*/React.createElement(\"span\", null, Icon && /*#__PURE__*/React.createElement(Icon, {\n    size: 16,\n    strokeWidth: 2\n  }), \" \", headerData.title)), /*#__PURE__*/React.createElement(\"div\", {\n    className: \"header-item\"\n  }, \"MID \", headerData.mid), /*#__PURE__*/React.createElement(\"div\", {\n    className: \"header-item\"\n  }, \"SAID \", headerData.said), /*#__PURE__*/React.createElement(\"div\", {\n    className: \"header-item\"\n  }, \"Rate Plan \", headerData.ratePlan), /*#__PURE__*/React.createElement(\"div\", {\n    className: \"header-item\"\n  }, headerData.locationDescription), /*#__PURE__*/React.createElement(\"div\", {\n    className: \"header-item\"\n  }, headerData.dateRange), /*#__PURE__*/React.createElement(\"div\", {\n    className: \"header-item\"\n  }, headerData.subtotal)), /*#__PURE__*/React.createElement(\"div\", {\n    className: `sub-container slide-section ${showHeader ? \"open\" : \"\"}`\n  }, /*#__PURE__*/React.createElement(\"div\", {\n    className: \"general-info\"\n  }, /*#__PURE__*/React.createElement(\"h3\", null, \"General Information\"), /*#__PURE__*/React.createElement(\"div\", {\n    className: \"info-grid\"\n  }, /*#__PURE__*/React.createElement(\"div\", {\n    className: \"info-column\"\n  }, infoLeft.map(item => /*#__PURE__*/React.createElement(InfoRow, _extends({\n    key: item.label\n  }, item)))), /*#__PURE__*/React.createElement(\"div\", {\n    className: \"info-column\"\n  }, infoRight.map(item => /*#__PURE__*/React.createElement(InfoRow, _extends({\n    key: item.label\n  }, item))))), /*#__PURE__*/React.createElement(UsageTable, {\n    usageData: usage\n  })), /*#__PURE__*/React.createElement(\"div\", {\n    className: \"calc-container\"\n  }, /*#__PURE__*/React.createElement(\"h3\", {\n    className: \"calc-header\",\n    onClick: () => setShowCalc(!showCalc)\n  }, /*#__PURE__*/React.createElement(\"span\", {\n    className: `arrow ${showCalc ? \"open\" : \"\"}`\n  }, \"\\u25BE\"), \" Calculated Values\"), /*#__PURE__*/React.createElement(\"div\", {\n    className: `slide-section ${showCalc ? \"open\" : \"\"}`\n  }, /*#__PURE__*/React.createElement(CalculationBox, {\n    title: \"Regular Values\",\n    values: regularValues\n  }), /*#__PURE__*/React.createElement(CalculationBox, {\n    title: \"Weather Values\",\n    values: weatherValues\n  }), /*#__PURE__*/React.createElement(CalculationBox, {\n    title: \"Daily-average Values\",\n    values: dailyAverageValues\n  })))));\n}\n\n// ------------------------- Main App -------------------------\nfunction App() {\n  const [data, setData] = useState(appsmith.model?.data || []);\n  const [filters, setFilters] = useState({\n    utility_type: \"\",\n    meter_id: \"\",\n    service_account_id: \"\",\n    service_address: \"\",\n    location_description: \"\"\n  });\n  const [filteredData, setFilteredData] = useState([]);\n  const [collapseAll, setCollapseAll] = useState(false);\n  const [showFilters, setShowFilters] = useState(false);\n\n  // Unique dropdown options\n  const options = useMemo(() => {\n    const unique = key => [...new Set(data.map(r => r[key]).filter(Boolean))];\n    return {\n      utility_type: unique(\"utility_type\"),\n      meter_id: unique(\"meter_id\"),\n      service_account_id: unique(\"service_account_id\"),\n      service_address: unique(\"service_address\"),\n      location_description: unique(\"location_description\")\n    };\n  }, [data]);\n  useEffect(() => {\n    const interval = setInterval(() => {\n      const newData = appsmith.model?.data || [];\n      if (newData.length && newData.length !== data.length) setData([...newData]);\n    }, 500);\n    return () => clearInterval(interval);\n  }, [data]);\n  useEffect(() => {\n    let filtered = [...data];\n    Object.entries(filters).forEach(([key, val]) => {\n      if (val) filtered = filtered.filter(r => r[key] === val);\n    });\n    setFilteredData(filtered);\n  }, [filters, data]);\n  const handleFilterChange = (key, value) => setFilters(prev => ({\n    ...prev,\n    [key]: value\n  }));\n  const clearFilters = () => setFilters({\n    utility_type: \"\",\n    meter_id: \"\",\n    service_account_id: \"\",\n    service_address: \"\",\n    location_description: \"\"\n  });\n  const FilterBar = () => /*#__PURE__*/React.createElement(\"div\", {\n    className: `filter-bar-container ${showFilters ? \"open\" : \"\"}`\n  }, /*#__PURE__*/React.createElement(\"div\", {\n    className: \"filter-grid\"\n  }, Object.keys(filters).map(key => /*#__PURE__*/React.createElement(\"div\", {\n    key: key,\n    className: \"filter-item\"\n  }, /*#__PURE__*/React.createElement(\"select\", {\n    value: filters[key],\n    onChange: e => handleFilterChange(key, e.target.value)\n  }, /*#__PURE__*/React.createElement(\"option\", {\n    value: \"\"\n  }, key.replace(/_/g, \" \").replace(/\\b\\w/g, c => c.toUpperCase())), options[key].map(opt => /*#__PURE__*/React.createElement(\"option\", {\n    key: opt,\n    value: opt\n  }, opt)))))), /*#__PURE__*/React.createElement(\"div\", {\n    className: \"filter-footer\"\n  }, /*#__PURE__*/React.createElement(\"button\", {\n    className: \"clear-btn\",\n    onClick: clearFilters\n  }, \"Clear\")));\n  const CollapseAllIcon = LucideIcons['FoldVertical'];\n  const ExpandAllIcon = LucideIcons['UnfoldVertical'];\n  return /*#__PURE__*/React.createElement(\"div\", null, /*#__PURE__*/React.createElement(\"div\", {\n    className: \"top-toolbar\"\n  }, /*#__PURE__*/React.createElement(\"div\", {\n    className: \"toolbar-left\"\n  }, /*#__PURE__*/React.createElement(\"span\", {\n    className: \"bill-count\"\n  }, \"Bill Blocks total: \", /*#__PURE__*/React.createElement(\"b\", null, filteredData.length))), /*#__PURE__*/React.createElement(\"div\", {\n    className: \"toolbar-right\"\n  }, /*#__PURE__*/React.createElement(\"button\", {\n    className: \"icon-btn\",\n    title: collapseAll ? \"Expand All\" : \"Collapse All\",\n    onClick: () => setCollapseAll(!collapseAll)\n  }, collapseAll ? /*#__PURE__*/React.createElement(ExpandAllIcon, null) : /*#__PURE__*/React.createElement(CollapseAllIcon, null)), /*#__PURE__*/React.createElement(\"button\", {\n    className: \"icon-btn filters\",\n    title: \"Toggle Filters\",\n    onClick: () => setShowFilters(!showFilters)\n  }, /*#__PURE__*/React.createElement(LucideIcons.Filter, {\n    size: 16\n  }), /*#__PURE__*/React.createElement(\"span\", {\n    className: \"filter-label\"\n  }, \"Filters\")))), /*#__PURE__*/React.createElement(FilterBar, null), filteredData.map((record, i) => /*#__PURE__*/React.createElement(BillRecord, {\n    key: i,\n    record: record,\n    collapseAll: collapseAll\n  })));\n}\nReactDOM.render(/*#__PURE__*/React.createElement(App, null), document.getElementById(\"root\"));"
  },
  "theme": "{{appsmith.theme}}",
  "topRow": 2,
  "type": "CUSTOM_WIDGET",
  "uncompiledSrcDoc": {
    "css": "body {\n  margin: 0;\n  font-family: \"Inter\", \"Segoe UI\", Arial, sans-serif;\n}\n\n/* ===== Header Bar ===== */\n.header-bar {\n  display: flex;\n  align-items: center;\n  background-color: #001f54;\n  color: #fff;\n  font-size: 13px;\n  font-weight: 500;\n  padding: 6px 10px;\n  flex-wrap: wrap;\n  border-radius: 4px 4px 0 0;\n}\n\n.header-item {\n  padding: 4px 10px;\n  border-right: 1px solid rgba(255, 255, 255, 0.2);\n}\n\n.header-item:last-child {\n  border-right: none;\n}\n\n.header-item.title {\n  font-weight: 600;\n  display: inline-flex;\n  align-items: center;\n  gap: 4px;\n  text-transform: capitalize;\n  background: #082E69;\n  justify-content: center;\n}\n\n.utility-title svg {\n  stroke: #fff;\n  vertical-align: middle;\n  position: relative;\n  top: -1px;\n}\n\n/* ===== General Info + Calculation Container Shared Style ===== */\n.general-info,\n.calc-container {\n  background: #fff;\n  border-radius: 6px;\n  padding: 16px 20px;\n  margin: 12px;\n  box-shadow: 0 2px 6px rgba(0, 0, 0, 0.08);\n  color: #0a0a0a;\n}\n\n.general-info h3,\n.calc-container h3 {\n  font-weight: 700;\n  font-size: 16px;\n  color: #002050;\n  margin-bottom: 12px;\n}\n\n/* ===== Info Grid (2 columns) ===== */\n.info-grid {\n  display: grid;\n  grid-template-columns: 1fr 1fr;\n  gap: 10px 20px;\n}\n\n.info-column {\n  display: flex;\n  flex-direction: column;\n  gap: 4px;\n}\n\n/* ===== Info Row ===== */\n.info-row {\n  display: flex;\n  justify-content: space-between;\n  align-items: center;\n  padding: 6px 10px;\n  font-size: 13px;\n  border-bottom: 1px solid #f1f2f4;\n  border-radius: 2px;\n  background-color: #fff;\n}\n\n.info-row:nth-child(odd) {\n  background-color: #F1F2F4;\n}\n\n.info-label {\n  font-weight: 600;\n  color: #222;\n  flex: 1;\n  white-space: nowrap;\n}\n\n.info-value {\n  flex: 1;\n  text-align: right;\n  color: #111;\n  font-weight: 500;\n}\n\n.unit {\n  color: #666;\n  font-size: 12px;\n  margin-left: 3px;\n}\n\n/* ===== No Data ===== */\n.no-data {\n  text-align: center;\n  color: #777;\n  font-style: italic;\n  padding: 12px;\n}\n\n/* ===== Usage Section ===== */\n.usage-section {\n  margin-top: 20px;\n}\n\n.usage-section h3 {\n  font-weight: 700;\n  font-size: 15px;\n  color: #002050;\n  margin-bottom: 10px;\n}\n\n.usage-table {\n  width: 100%;\n  border-collapse: collapse;\n  font-size: 13px;\n}\n\n.usage-table th {\n  text-align: left;\n  background-color: #f1f4f8;\n  color: #002050;\n  font-weight: 600;\n  padding: 8px 10px;\n}\n\n.usage-table td {\n  padding: 8px 10px;\n  border-top: 1px solid #eee;\n}\n\n.usage-table tr:nth-child(odd) {\n  background-color: #F1F2F4;\n}\n\n/* ===== Calculation Section ===== */\n.calc-section {\n  margin-top: 20px;\n}\n\n.calc-section h4 {\n  font-size: 14px;\n  font-weight: 600;\n  color: #0a0a0a;\n  margin-bottom: 16px;\n}\n/* ===== Collapsible Section Headers ===== */\n.collapsible-header,\n.calc-header {\n  cursor: pointer;\n  user-select: none;\n}\n\n.arrow {\n  display: inline-block;\n  font-size: 18px;\n  transition: transform 0.3s ease;\n  transform: rotate(-90deg); /* Default → right */\n  margin-right: 6px;\n}\n\n.arrow.open {\n  transform: rotate(0deg); /* Open ↓ down */\n}\n\n/* ===== Slide Animation ===== */\n.slide-section {\n  max-height: 0;\n  opacity: 0;\n  overflow: hidden;\n  transform: translateY(-5px);\n  transition: all 0.4s ease-in-out;\n}\n\n.slide-section.open {\n  max-height: fit-content;\n  opacity: 1;\n  transform: translateY(0);\n\tpadding-bottom: 10px;\n}\n.sub-container{\n\tbackground-color: #F8FAFC;\n}\n/* ===== Filter Bar with Selects ===== */\n.filter-bar {\n  background: #f8fafc;\n  border: 1px solid #d9e2ec;\n  border-radius: 6px;\n  padding: 10px 16px;\n  margin: 10px 12px 20px;\n  box-shadow: 0 1px 4px rgba(0, 0, 0, 0.05);\n}\n\n.filter-row {\n  display: flex;\n  gap: 10px;\n  flex-wrap: wrap;\n  align-items: center;\n}\n\n.filter-row select {\n  flex: 1;\n  min-width: 160px;\n  padding: 10px;\n  border: 1px solid #cbd5e1;\n  border-radius: 4px;\n  font-size: 13px;\n  background: #fff;\n  color: #0a0a0a;\n  cursor: pointer;\n}\n\n.filter-row select:focus {\n  border-color: #2563eb;\n  box-shadow: 0 0 0 2px rgba(37, 99, 235, 0.15);\n}\n\n.filter-row button {\n  background-color: #001f54;\n  color: #fff;\n  border: none;\n  border-radius: 4px;\n  padding: 6px 12px;\n  cursor: pointer;\n  font-size: 13px;\n  font-weight: 600;\n}\n\n.filter-row button:hover {\n  background-color: #003c8f;\n}\n\n/* === Top Toolbar === */\n.top-toolbar {\n  display: flex;\n  justify-content: space-between;\n  align-items: center;\n  padding: 8px 0px 0px 10px;\n}\n\n.bill-count {\n  font-size: 14px;\n  color: #001f54;\n}\n\n.toolbar-right {\n  display: flex;\n  align-items: center;\n  gap: 8px;\n}\n\n.icon-btn {\n  background: transparent;\n  border: none;\n  padding: 6px 10px;\n  display: flex;\n  align-items: center;\n  gap: 6px;\n  cursor: pointer;\n  color: #001f54;\n  font-weight: 600;\n  transition: background 0.2s ease;\n}\n\n.filters {\n\tbackground: #F1F2F4;\n  border: 1px solid #F1F2F4;\n\tborder-radius:3px;\n}\n.filters svg {\n\theight:24px;\n}\n\n.filters:hover {\n  color: #1846b0;\n}\n\n.filter-label {\n  font-size: 13px;\n}\n\n/* === Filter Bar Hide/Show Animation === */\n.filter-bar-wrapper {\n  max-height: 0;\n  overflow: hidden;\n  transition: max-height 0.4s ease;\n}\n\n.filter-bar-wrapper.open {\n  max-height: 200px;\n  transition: max-height 0.4s ease;\n}\n\n/* ========== Filter Bar Container ========== */\n.filter-bar-container {\n  background: #F1F2F4;\n  border-radius: 6px;\n  box-shadow: 0 2px 6px rgba(0,0,0,0.08);\n  margin: 0px 0 20px;\n  padding: 0 16px;\n  overflow: hidden;\n  max-height: 0;\n  opacity: 0;\n  transform: translateY(-8px);\n  transition: all 0.4s ease-in-out;\n}\n\n.filter-bar-container.open {\n  max-height: 500px;\n  opacity: 1;\n  transform: translateY(0);\n  padding-top: 16px;\n  padding-bottom: 16px;\n}\n\n/* ========== Grid Layout for Select Boxes ========== */\n.filter-grid {\n  display: grid;\n  grid-template-columns: repeat(3, 1fr);\n  gap: 12px 20px;\n}\n\n.filter-item select {\n  width: 100%;\n  padding: 6px 8px;\n  font-size: 13px;\n  border-radius: 4px;\n  border: 1px solid #ccc;\n  background: #fff;\n  color: #222;\n}\n\n/* ========== Responsive Grid ========== */\n\n@media (max-width: 600px) {\n  .filter-grid {\n    grid-template-columns: repeat(2, 1fr);\n  }\n}\n@media (max-width: 300px) {\n  .filter-grid {\n    grid-template-columns:  1fr;\n  }\n}\n\n/* ========== Footer ========== */\n.filter-footer {\n  display: flex;\n  justify-content: flex-end;\n  margin-top: 16px;\n}\n\n.clear-btn {\n  background: transparent;\n  color: #1846b0;\n  border: none;\n  padding: 6px 12px;\n  font-weight: 600;\n  font-size: 13px;\n  cursor: pointer;\n  transition: background 0.3s;\n\ttext-decoration: underline;\n}\n\n\n\n\n/* ===== Responsive ===== */\n/* @media (max-width: 768px) {\n  .info-grid {\n    grid-template-columns: 1fr;\n  }\n}*/\n",
    "html": "<!-- no need to write html, head, body tags, it is handled by the widget -->\n<div id=\"root\"></div>\n",
    "js": "import React, { useState, useEffect, useMemo } from \"https://esm.sh/react@18.2.0\";\nimport ReactDOM from \"https://esm.sh/react-dom@18.2.0\";\nimport * as LucideIcons from \"https://esm.sh/lucide-react@0.292.0\";\n\n// ------------------------- Info Row -------------------------\nfunction InfoRow({ label, value }) {\n  return (\n    <div className=\"info-row\">\n      <span className=\"info-label\">{label}</span>\n      <span className=\"info-value\">{value}</span>\n    </div>\n  );\n}\n\n// ------------------------- Usage Table -------------------------\nfunction UsageTable({ usageData }) {\n  if (!usageData?.length) return null;\n  return (\n    <div className=\"usage-section\">\n      <h3>Usage Charges</h3>\n      <table className=\"usage-table\">\n        <tbody>\n          {usageData.map((row, i) => (\n            <tr key={i}>\n              <td>{row.value || \"-\"}</td>\n              <td>{row.usage || \"-\"}</td>\n              <td>{row.uom || \"-\"}</td>\n              <td>\n                <b>${row.charge?.toFixed(2) || \"0.00\"}</b>\n              </td>\n              <td>{row.description || \"-\"}</td>\n            </tr>\n          ))}\n        </tbody>\n      </table>\n    </div>\n  );\n}\n\n// ------------------------- Calculation Box -------------------------\nfunction CalculationBox({ title, values }) {\n  if (!values?.length) return null;\n\n  const midIndex = Math.ceil(values.length / 2);\n  const leftValues = values.slice(0, midIndex);\n  const rightValues = values.slice(midIndex);\n\n  return (\n    <div className=\"calc-section\">\n      <h4>{title}</h4>\n      <div className=\"info-grid\">\n        <div className=\"info-column\">\n          {leftValues.map((item, i) => (\n            <InfoRow\n              key={i}\n              label={item.name || \"-\"}\n              value={\n                <>\n                  {item.value || \"-\"} <span className=\"unit\">{item.units || \"\"}</span>\n                </>\n              }\n            />\n          ))}\n        </div>\n        <div className=\"info-column\">\n          {rightValues.map((item, i) => (\n            <InfoRow\n              key={i}\n              label={item.name || \"-\"}\n              value={\n                <>\n                  {item.value || \"-\"} <span className=\"unit\">{item.units || \"\"}</span>\n                </>\n              }\n            />\n          ))}\n        </div>\n      </div>\n    </div>\n  );\n}\n\n// ------------------------- Bill Record -------------------------\nfunction BillRecord({ record, collapseAll }) {\n  const [showHeader, setShowHeader] = useState(true);\n  const [showCalc, setShowCalc] = useState(false);\n\n  useEffect(() => {\n    setShowHeader(!collapseAll);\n  }, [collapseAll]);\n\n  const usage = record.usage || [];\n  const weatherValues = record.weathervalues || [];\n\n  const dailyAverageValues = (record.regulardailyvalues || []).filter((v) =>\n    v.name?.toLowerCase().includes(\"daily\")\n  );\n  const regularValues = (record.regulardailyvalues || []).filter(\n    (v) => !v.name?.toLowerCase().includes(\"daily\")\n  );\n\n  const headerData = {\n    title:\n      record.utility_type?.charAt(0).toUpperCase() +\n      record.utility_type?.slice(1).toLowerCase(),\n    mid: record.meter_id || \"-\",\n    said: record.service_account_id || \"-\",\n    ratePlan: record.rate_plan || \"-\",\n    locationDescription: record.location_description || \"-\",\n    dateRange:\n      record.billing_start_date && record.billing_end_date\n        ? `${record.billing_start_date} - ${record.billing_end_date}`\n        : \"-\",\n    subtotal: `$${record.current_charges || \"0.00\"}`,\n  };\n\n  const infoLeft = [\n    { label: \"Bill SubTotal\", value: `$${record.current_charges || \"-\"}` },\n    { label: \"Virtual Account Id\", value: record.virtual_account_id || \"-\" },\n    { label: \"Service Account Id\", value: record.service_account_id || \"-\" },\n    { label: \"Service Address\", value: record.service_address || \"-\" },\n    { label: \"Service Zip\", value: record.service_zip || \"-\" },\n    { label: \"Meter Id\", value: record.meter_id || \"-\" },\n    { label: \"Delivery Location\", value: record.delivery_location || \"-\" },\n    { label: \"Vendor Type\", value: record.vendor_type || \"-\" },\n    { label: \"Location Address\", value: record.location_address || \"-\" },\n  ];\n\n  const infoRight = [\n    { label: \"Location Description\", value: record.location_description || \"-\" },\n    { label: \"Division\", value: record.division || \"-\" },\n    { label: \"Service Start Date\", value: record.billing_start_date || \"-\" },\n    { label: \"Service End Date\", value: record.billing_end_date || \"-\" },\n    {\n      label: \"Days Of Service\",\n      value:\n        record.days_of_service && record.service_date_method\n          ? `${record.days_of_service} (${record.service_date_method})`\n          : \"-\",\n    },\n    {\n      label: \"Adjusted Service End Date\",\n      value: record.adjusted_service_end_date || \"-\",\n    },\n    { label: \"Rate Plan\", value: record.rate_plan || \"-\" },\n    { label: \"Estimated\", value: record.estimated ? \"YES\" : \"NO\" },\n    { label: \"Prior Meter Reading\", value: record.prior_meter_reading || \"-\" },\n  ];\n\n  const utilityIcons = {\n    CABLE: \"Tv\",\n    CARBONDIOXIDE: \"Wind\",\n    CHILLEDWATER: \"Snowflake\",\n    DIESEL: \"Fuel\",\n    ELECTRIC: \"Zap\",\n    FIREPROTECTION: \"Shield\",\n    FUELCELL: \"Battery\",\n    HOTWATER: \"Flame\",\n    INTERNET: \"Wifi\",\n    IRRIGATION: \"Sprout\",\n    LIGHTING: \"Lightbulb\",\n    NATURALGAS: \"Flame\",\n    NG_COGEN: \"Factory\",\n    NITROGEN: \"FlaskConical\",\n    OIL2: \"Fuel\",\n    OIL4: \"Fuel\",\n    OIL6: \"Fuel\",\n    OTHER: \"Package\",\n    OXYGEN: \"Activity\",\n    PESTCONTROL: \"Bug\",\n    PROPANE: \"Flame\",\n    REFUSE: \"Trash2\",\n    SEWER: \"Waves\",\n    SOLARPV: \"Haze\",\n    STEAM: \"CloudFog\",\n    STORMDRAIN: \"CloudRain\",\n    STORMWATER: \"CloudRainWind\",\n    TELEPHONE: \"UtilityPole\",\n    UNLEADEDFUEL: \"Fuel\",\n    UTILITYGAS: \"Flame\",\n    WATER: \"Droplet\",\n  };\n\t\n  const iconName = utilityIcons[record.utility_type?.toUpperCase()] || \"Factory\";\n  const Icon = LucideIcons[iconName];\n\n  return (\n    <div className=\"container\">\n      <div className=\"header-bar collapsible-header\" onClick={() => setShowHeader(!showHeader)}>\n        <span className={`arrow ${showHeader ? \"open\" : \"\"}`}>▾</span>\n        <div className=\"header-item title utility-title\">\n          <span>{Icon && <Icon size={16} strokeWidth={2} />} {headerData.title}</span>\n        </div>\n        <div className=\"header-item\">MID {headerData.mid}</div>\n        <div className=\"header-item\">SAID {headerData.said}</div>\n        <div className=\"header-item\">Rate Plan {headerData.ratePlan}</div>\n        <div className=\"header-item\">{headerData.locationDescription}</div>\n        <div className=\"header-item\">{headerData.dateRange}</div>\n        <div className=\"header-item\">{headerData.subtotal}</div>\n      </div>\n\n      <div className={`sub-container slide-section ${showHeader ? \"open\" : \"\"}`}>\n        <div className=\"general-info\">\n          <h3>General Information</h3>\n          <div className=\"info-grid\">\n            <div className=\"info-column\">{infoLeft.map((item) => <InfoRow key={item.label} {...item} />)}</div>\n            <div className=\"info-column\">{infoRight.map((item) => <InfoRow key={item.label} {...item} />)}</div>\n          </div>\n          <UsageTable usageData={usage} />\n        </div>\n\n        <div className=\"calc-container\">\n          <h3 className=\"calc-header\" onClick={() => setShowCalc(!showCalc)}>\n            <span className={`arrow ${showCalc ? \"open\" : \"\"}`}>▾</span> Calculated Values\n          </h3>\n          <div className={`slide-section ${showCalc ? \"open\" : \"\"}`}>\n            <CalculationBox title=\"Regular Values\" values={regularValues} />\n            <CalculationBox title=\"Weather Values\" values={weatherValues} />\n            <CalculationBox title=\"Daily-average Values\" values={dailyAverageValues} />\n          </div>\n        </div>\n      </div>\n    </div>\n  );\n}\n\n// ------------------------- Main App -------------------------\nfunction App() {\n  const [data, setData] = useState(appsmith.model?.data || []);\n  const [filters, setFilters] = useState({\n    utility_type: \"\",\n    meter_id: \"\",\n    service_account_id: \"\",\n    service_address: \"\",\n    location_description: \"\",\n  });\n  const [filteredData, setFilteredData] = useState([]);\n  const [collapseAll, setCollapseAll] = useState(false);\n  const [showFilters, setShowFilters] = useState(false);\n\n  // Unique dropdown options\n  const options = useMemo(() => {\n    const unique = (key) => [...new Set(data.map((r) => r[key]).filter(Boolean))];\n    return {\n      utility_type: unique(\"utility_type\"),\n      meter_id: unique(\"meter_id\"),\n      service_account_id: unique(\"service_account_id\"),\n      service_address: unique(\"service_address\"),\n      location_description: unique(\"location_description\"),\n    };\n  }, [data]);\n\n  useEffect(() => {\n    const interval = setInterval(() => {\n      const newData = appsmith.model?.data || [];\n      if (newData.length && newData.length !== data.length) setData([...newData]);\n    }, 500);\n    return () => clearInterval(interval);\n  }, [data]);\n\n  useEffect(() => {\n    let filtered = [...data];\n    Object.entries(filters).forEach(([key, val]) => {\n      if (val) filtered = filtered.filter((r) => r[key] === val);\n    });\n    setFilteredData(filtered);\n  }, [filters, data]);\n\n  const handleFilterChange = (key, value) => setFilters((prev) => ({ ...prev, [key]: value }));\n\n  const clearFilters = () =>\n    setFilters({\n      utility_type: \"\",\n      meter_id: \"\",\n      service_account_id: \"\",\n      service_address: \"\",\n      location_description: \"\",\n    });\n\n  const FilterBar = () => (\n  <div className={`filter-bar-container ${showFilters ? \"open\" : \"\"}`}>\n    <div className=\"filter-grid\">\n      {Object.keys(filters).map((key) => (\n        <div key={key} className=\"filter-item\">\n          <select\n            value={filters[key]}\n            onChange={(e) => handleFilterChange(key, e.target.value)}\n          >\n            <option value=\"\">\n              {key.replace(/_/g, \" \").replace(/\\b\\w/g, (c) => c.toUpperCase())}\n            </option>\n            {options[key].map((opt) => (\n              <option key={opt} value={opt}>\n                {opt}\n              </option>\n            ))}\n          </select>\n        </div>\n      ))}\n    </div>\n\n    <div className=\"filter-footer\">\n      <button className=\"clear-btn\" onClick={clearFilters}>\n        Clear\n      </button>\n    </div>\n  </div>\n);\n\n\t\n\tconst CollapseAllIcon = LucideIcons['FoldVertical']\n\n  const ExpandAllIcon = LucideIcons['UnfoldVertical']\n\n  return (\n    <div>\n      {/* === Top Control Bar === */}\n      <div className=\"top-toolbar\">\n        <div className=\"toolbar-left\">\n          <span className=\"bill-count\">Bill Blocks total: <b>{filteredData.length}</b></span>\n        </div>\n\t\t\t\t\t\t<div className=\"toolbar-right\">\n\t\t\t\t\t\t\t<button\n\t\t\t\t\t\t\t\tclassName=\"icon-btn\"\n\t\t\t\t\t\t\t\ttitle={collapseAll ? \"Expand All\" : \"Collapse All\"}\n\t\t\t\t\t\t\t\tonClick={() => setCollapseAll(!collapseAll)}\n\t\t\t\t\t\t\t>\n\t\t\t\t\t\t\t\t{collapseAll ? <ExpandAllIcon /> : <CollapseAllIcon />}\n\t\t\t\t\t\t\t</button>\n\t\t\t\t\t\t\t<button\n\t\t\t\t\t\t\t\tclassName=\"icon-btn filters\"\n\t\t\t\t\t\t\t\ttitle=\"Toggle Filters\"\n\t\t\t\t\t\t\t\tonClick={() => setShowFilters(!showFilters)}\n\t\t\t\t\t\t\t>\n\t\t\t\t\t\t\t\t<LucideIcons.Filter size={16} />\n\t\t\t\t\t\t\t\t<span className=\"filter-label\">Filters</span>\n\t\t\t\t\t\t\t</button>\n\t\t\t\t\t\t</div>\n      </div>\n\n      <FilterBar />\n\n      {filteredData.map((record, i) => (\n        <BillRecord key={i} record={record} collapseAll={collapseAll} />\n      ))}\n    </div>\n  );\n}\n\nReactDOM.render(<App />, document.getElementById(\"root\"));\n"
  },
  "version": 1,
  "widgetId": "afe3r1pu65",
  "widgetName": "Custom2"
}