{
  "gitSyncId": "68f08f3128a92f6fcd2cb504_ad7ff8ba-3bb3-4e81-8407-bb6cbfba8219",
  "id": "Analytics_EnergyConsumptionHelper.getUtilityTable",
  "pluginId": "js-plugin",
  "pluginType": "JS",
  "unpublishedAction": {
    "actionConfiguration": {
      "encodeParamsToggle": true,
      "jsArguments": [],
      "paginationType": "NONE",
      "timeoutInMillisecond": 10000
    },
    "collectionId": "Analytics_EnergyConsumptionHelper",
    "confirmBeforeExecute": false,
    "datasource": {
      "isAutoGenerated": false,
      "name": "UNUSED_DATASOURCE",
      "pluginId": "js-plugin"
    },
    "dynamicBindingPathList": [
      {
        "key": "body"
      }
    ],
    "fullyQualifiedName": "EnergyConsumptionHelper.getUtilityTable",
    "name": "getUtilityTable",
    "pageId": "Analytics",
    "runBehaviour": "MANUAL",
    "userSetOnLoad": false
  }
}