{
  "animateLoading": true,
  "backgroundColor": "{{appsmith.theme.colors.primaryColor}}",
  "borderColor": "transparent",
  "borderRadius": "{{appsmith.theme.borderRadius.appBorderRadius}}",
  "borderWidth": "0",
  "bottomRow": 113,
  "boxShadow": "none",
  "children": [
    {
      "bottomRow": 990,
      "boxShadow": "none",
      "canExtend": false,
      "dynamicBindingPathList": [],
      "dynamicTriggerPathList": [],
      "flexLayers": [],
      "isLoading": false,
      "isVisible": true,
      "key": "3bxpm5fkyq",
      "leftColumn": 0,
      "minHeight": 400,
      "mobileBottomRow": 3300,
      "mobileLeftColumn": 0,
      "mobileRightColumn": 960,
      "mobileTopRow": 0,
      "needsErrorInfo": false,
      "parentColumnSpace": 1,
      "parentId": "x099osugax",
      "parentRowSpace": 1,
      "renderMode": "CANVAS",
      "rightColumn": 960,
      "shouldScrollContents": false,
      "topRow": 0,
      "type": "CANVAS_WIDGET",
      "version": 1,
      "widgetId": "m1e1yrlycp",
      "widgetName": "MECChartCanvas"
    }
  ],
  "dynamicBindingPathList": [
    {
      "key": "borderRadius"
    },
    {
      "key": "backgroundColor"
    }
  ],
  "dynamicHeight": "AUTO_HEIGHT",
  "dynamicTriggerPathList": [],
  "flexVerticalAlignment": "start",
  "isCanvas": true,
  "isLoading": false,
  "isVisible": true,
  "key": "z6i1xpu5tv",
  "leftColumn": 0,
  "maxDynamicHeight": 9000,
  "minDynamicHeight": 4,
  "minWidth": 450,
  "mobileBottomRow": 140,
  "mobileLeftColumn": 0,
  "mobileRightColumn": 48,
  "mobileTopRow": 16,
  "needsErrorInfo": false,
  "originalBottomRow": 113,
  "originalTopRow": 14,
  "parentColumnSpace": 15,
  "parentId": "jta8d1riq2",
  "parentRowSpace": 10,
  "renderMode": "CANVAS",
  "responsiveBehavior": "fill",
  "rightColumn": 42,
  "shouldScrollContents": true,
  "topRow": 14,
  "type": "CONTAINER_WIDGET",
  "version": 1,
  "widgetId": "x099osugax",
  "widgetName": "MECChartContainer"
}