{
  "gitSyncId": "68f08f3128a92f6fcd2cb504_a1306d14-e180-4b92-a1a6-5eac0198ddb3",
  "id": "Analytics_OverTheYearsHelper.getYearlyMonthlyData",
  "pluginId": "js-plugin",
  "pluginType": "JS",
  "unpublishedAction": {
    "actionConfiguration": {
      "encodeParamsToggle": true,
      "jsArguments": [],
      "paginationType": "NONE",
      "timeoutInMillisecond": 10000
    },
    "collectionId": "Analytics_OverTheYearsHelper",
    "confirmBeforeExecute": false,
    "datasource": {
      "isAutoGenerated": false,
      "name": "UNUSED_DATASOURCE",
      "pluginId": "js-plugin"
    },
    "dynamicBindingPathList": [
      {
        "key": "body"
      }
    ],
    "fullyQualifiedName": "OverTheYearsHelper.getYearlyMonthlyData",
    "name": "getYearlyMonthlyData",
    "pageId": "Analytics",
    "runBehaviour": "MANUAL",
    "userSetOnLoad": false
  }
}